plantuml.py
plantuml-0.2.1.dist-info/DESCRIPTION.rst
plantuml-0.2.1.dist-info/METADATA
plantuml-0.2.1.dist-info/RECORD
plantuml-0.2.1.dist-info/WHEEL
plantuml-0.2.1.dist-info/metadata.json
plantuml-0.2.1.dist-info/top_level.txt
