Metadata-Version: 2.0
Name: plantuml
Version: 0.2.1
Summary: UNKNOWN
Home-page: https://github.com/dougn/python-plantuml/
Author: Doug Napoleone
Author-email: doug.napoleone+plantuml@gmail.com
License: BSD
Keywords: plantuml,uml
Platform: UNKNOWN
Classifier: Development Status :: 3 - Alpha
Classifier: Programming Language :: Python
Classifier: Programming Language :: Python :: 2.6
Classifier: Programming Language :: Python :: 2.7
Classifier: Intended Audience :: Developers
Classifier: Intended Audience :: System Administrators
Classifier: License :: OSI Approved :: BSD License
Classifier: Topic :: Internet :: WWW/HTTP
Classifier: Topic :: Utilities
Classifier: Topic :: Software Development :: Libraries :: Python Modules
Requires-Dist: httplib2
